[
  {
    "views": 18804,
    "clicks": 667,
    "ctr": 3.55,
    "cpc": 3.75,
    "sum": 2499.06,
    "atbs": 42,
    "orders": 12,
    "cr": 1.8,
    "shks": 13,
    "sum_price": 18756,
    "dates": ["2024-10-08"],
    "days": [
      {
        "date": "2024-10-08T03:00:00+03:00",
        "views": 18804,
        "clicks": 667,
        "ctr": 0,
        "cpc": 3.75,
        "sum": 2499.06,
        "atbs": 42,
        "orders": 12,
        "cr": 1.8,
        "shks": 13,
        "sum_price": 18756,
        "apps": [
          {
            "views": 8,
            "clicks": 0,
            "ctr": 0,
            "cpc": 0,
            "sum": 0.85,
            "atbs": 0,
            "orders": 0,
            "cr": 0,
            "shks": 0,
            "sum_price": 0,
            "nm": [
              {
                "name": "Нижнее белье комплект кружевное",
                "nmId": 186652711
              }
            ],
            "appType": 0
          },
          {
            "views": 1199,
            "clicks": 21,
            "ctr": 1.75,
            "cpc": 8.17,
            "sum": 171.58,
            "atbs": 1,
            "orders": 1,
            "cr": 4.76,
            "shks": 1,
            "sum_price": 1483,
            "nm": [
              {
                "views": 1199,
                "clicks": 21,
                "ctr": 1.75,
                "cpc": 8.17,
                "sum": 171.58,
                "atbs": 1,
                "orders": 1,
                "cr": 4.76,
                "shks": 1,
                "sum_price": 1483,
                "name": "Нижнее белье комплект кружевное",
                "nmId": 186652711
              }
            ],
            "appType": 1
          },
          {
            "views": 6946,
            "clicks": 249,
            "ctr": 3.58,
            "cpc": 3.69,
            "sum": 917.92,
            "atbs": 15,
            "orders": 2,
            "cr": 0.8,
            "shks": 2,
            "sum_price": 2858,
            "nm": [
              {
                "views": 6946,
                "clicks": 249,
                "ctr": 3.58,
                "cpc": 3.69,
                "sum": 917.92,
                "atbs": 15,
                "orders": 2,
                "cr": 0.8,
                "shks": 2,
                "sum_price": 2858,
                "name": "Нижнее белье комплект кружевное",
                "nmId": 186652711
              }
            ],
            "appType": 32
          },
          {
            "views": 10651,
            "clicks": 397,
            "ctr": 3.73,
            "cpc": 0,
            "sum": 1.41,
            "atbs": 26,
            "orders": 9,
            "cr": 2.27,
            "shks": 10,
            "sum_price": 14415,
            "nm": [
              {
                "views": 10651,
                "clicks": 397,
                "ctr": 3.73,
                "cpc": 3.55,
                "sum": 1408.71,
                "atbs": 26,
                "orders": 9,
                "cr": 2.27,
                "shks": 10,
                "sum_price": 14415,
                "name": "Нижнее белье комплект кружевное",
                "nmId": 186652711
              }
            ],
            "appType": 64
          }
        ]
      }
    ],
    "boosterStats": [
      {
        "date": "2024-10-08T03:00:00+03:00",
        "nm": 186652711,
        "avg_position": 0
      },
      {
        "date": "2024-10-08T03:00:00+03:00",
        "nm": 186652711,
        "avg_position": 0
      },
      {
        "date": "2024-10-08T03:00:00+03:00",
        "nm": 186652711,
        "avg_position": 0
      },
      {
        "date": "2024-10-08T03:00:00+03:00",
        "nm": 186652711,
        "avg_position": 0
      },
      {
        "date": "2024-10-08T03:00:00+03:00",
        "nm": 186652711,
        "avg_position": 0
      },
      {
        "date": "2024-10-08T03:00:00+03:00",
        "nm": 186652711,
        "avg_position": 0
      },
      {
        "date": "2024-10-08T03:00:00+03:00",
        "nm": 186652711,
        "avg_position": 0
      },
      {
        "date": "2024-10-08T03:00:00+03:00",
        "nm": 186652711,
        "avg_position": 0
      },
      {
        "date": "2024-10-08T03:00:00+03:00",
        "nm": 186652711,
        "avg_position": 0
      },
      {
        "date": "2024-10-08T03:00:00+03:00",
        "nm": 186652711,
        "avg_position": 0
      },
      {
        "date": "2024-10-08T03:00:00+03:00",
        "nm": 186652711,
        "avg_position": 0
      },
      {
        "date": "2024-10-08T03:00:00+03:00",
        "nm": 186652711,
        "avg_position": 0
      },
      {
        "date": "2024-10-08T03:00:00+03:00",
        "nm": 186652711,
        "avg_position": 0
      },
      {
        "date": "2024-10-08T03:00:00+03:00",
        "nm": 186652711,
        "avg_position": 0
      },
      {
        "date": "2024-10-08T03:00:00+03:00",
        "nm": 186652711,
        "avg_position": 0
      },
      {
        "date": "2024-10-08T03:00:00+03:00",
        "nm": 186652711,
        "avg_position": 0
      },
      {
        "date": "2024-10-08T03:00:00+03:00",
        "nm": 186652711,
        "avg_position": 0
      },
      {
        "date": "2024-10-08T03:00:00+03:00",
        "nm": 186652711,
        "avg_position": 0
      },
      {
        "date": "2024-10-08T03:00:00+03:00",
        "nm": 186652711,
        "avg_position": 0
      },
      {
        "date": "2024-10-08T03:00:00+03:00",
        "nm": 186652711,
        "avg_position": 0
      },
      {
        "date": "2024-10-08T03:00:00+03:00",
        "nm": 186652711,
        "avg_position": 0
      },
      {
        "date": "2024-10-08T03:00:00+03:00",
        "nm": 186652711,
        "avg_position": 0
      },
      {
        "date": "2024-10-08T03:00:00+03:00",
        "nm": 186652711,
        "avg_position": 0
      },
      {
        "date": "2024-10-08T03:00:00+03:00",
        "nm": 165157224,
        "avg_position": 0
      },
      {
        "date": "2024-10-08T03:00:00+03:00",
        "nm": 242293333,
        "avg_position": 0
      },
      {
        "date": "2024-10-08T03:00:00+03:00",
        "nm": 235991430,
        "avg_position": 0
      },
      {
        "date": "2024-10-08T03:00:00+03:00",
        "nm": 218974848,
        "avg_position": 0
      },
      {
        "date": "2024-10-08T03:00:00+03:00",
        "nm": 151368890,
        "avg_position": 0
      },
      {
        "date": "2024-10-08T03:00:00+03:00",
        "nm": 208178050,
        "avg_position": 0
      },
      {
        "date": "2024-10-08T03:00:00+03:00",
        "nm": 233234033,
        "avg_position": 0
      },
      {
        "date": "2024-10-08T03:00:00+03:00",
        "nm": 235991430,
        "avg_position": 0
      },
      {
        "date": "2024-10-08T03:00:00+03:00",
        "nm": 165157224,
        "avg_position": 0
      },
      {
        "date": "2024-10-08T03:00:00+03:00",
        "nm": 200021733,
        "avg_position": 0
      },
      {
        "date": "2024-10-08T03:00:00+03:00",
        "nm": 218974848,
        "avg_position": 0
      },
      {
        "date": "2024-10-08T03:00:00+03:00",
        "nm": 147497597,
        "avg_position": 0
      },
      {
        "date": "2024-10-08T03:00:00+03:00",
        "nm": 242293333,
        "avg_position": 0
      },
      {
        "date": "2024-10-08T03:00:00+03:00",
        "nm": 165157224,
        "avg_position": 0
      },
      {
        "date": "2024-10-08T03:00:00+03:00",
        "nm": 235991430,
        "avg_position": 0
      },
      {
        "date": "2024-10-08T03:00:00+03:00",
        "nm": 218974848,
        "avg_position": 0
      },
      {
        "date": "2024-10-08T03:00:00+03:00",
        "nm": 200021733,
        "avg_position": 0
      }
    ],
    "advertId": 18854755
  },
  {
    "views": 31436,
    "clicks": 1156,
    "ctr": 3.68,
    "cpc": 2.91,
    "sum": 3365.84,
    "atbs": 39,
    "orders": 7,
    "cr": 0.61,
    "shks": 7,
    "sum_price": 12657,
    "dates": ["2024-10-08"],
    "days": [
      {
        "date": "2024-10-08T03:00:00+03:00",
        "views": 31436,
        "clicks": 1156,
        "ctr": 0,
        "cpc": 2.91,
        "sum": 3365.84,
        "atbs": 39,
        "orders": 7,
        "cr": 0.61,
        "shks": 7,
        "sum_price": 12657,
        "apps": [
          {
            "views": 12,
            "clicks": 0,
            "ctr": 0,
            "cpc": 0,
            "sum": 0.91,
            "atbs": 0,
            "orders": 0,
            "cr": 0,
            "shks": 0,
            "sum_price": 0,
            "nm": [
              {
                "name": "Кружевное нижнее белье комплект",
                "nmId": 165157224
              }
            ],
            "appType": 0
          },
          {
            "views": 1962,
            "clicks": 39,
            "ctr": 1.99,
            "cpc": 5.41,
            "sum": 211.15,
            "atbs": 0,
            "orders": 0,
            "cr": 0,
            "shks": 0,
            "sum_price": 0,
            "nm": [
              {
                "views": 1962,
                "clicks": 39,
                "ctr": 1.99,
                "cpc": 5.41,
                "sum": 211.15,
                "atbs": 0,
                "orders": 0,
                "cr": 0,
                "shks": 0,
                "sum_price": 0,
                "name": "Кружевное нижнее белье комплект",
                "nmId": 165157224
              }
            ],
            "appType": 1
          },
          {
            "views": 11546,
            "clicks": 407,
            "ctr": 3.53,
            "cpc": 3.06,
            "sum": 1244.35,
            "atbs": 17,
            "orders": 4,
            "cr": 0.98,
            "shks": 4,
            "sum_price": 7239,
            "nm": [
              {
                "views": 11546,
                "clicks": 407,
                "ctr": 3.53,
                "cpc": 3.06,
                "sum": 1244.35,
                "atbs": 17,
                "orders": 4,
                "cr": 0.98,
                "shks": 4,
                "sum_price": 7239,
                "name": "Кружевное нижнее белье комплект",
                "nmId": 165157224
              }
            ],
            "appType": 32
          },
          {
            "views": 17916,
            "clicks": 710,
            "ctr": 3.96,
            "cpc": 0,
            "sum": 1.91,
            "atbs": 22,
            "orders": 3,
            "cr": 0.42,
            "shks": 3,
            "sum_price": 5418,
            "nm": [
              {
                "views": 17916,
                "clicks": 710,
                "ctr": 3.96,
                "cpc": 2.69,
                "sum": 1909.43,
                "atbs": 22,
                "orders": 3,
                "cr": 0.42,
                "shks": 3,
                "sum_price": 5418,
                "name": "Кружевное нижнее белье комплект",
                "nmId": 165157224
              }
            ],
            "appType": 64
          }
        ]
      }
    ],
    "boosterStats": [
      {
        "date": "2024-10-08T03:00:00+03:00",
        "nm": 165157224,
        "avg_position": 0
      },
      {
        "date": "2024-10-08T03:00:00+03:00",
        "nm": 165157224,
        "avg_position": 0
      },
      {
        "date": "2024-10-08T03:00:00+03:00",
        "nm": 165157224,
        "avg_position": 0
      },
      {
        "date": "2024-10-08T03:00:00+03:00",
        "nm": 165157224,
        "avg_position": 0
      },
      {
        "date": "2024-10-08T03:00:00+03:00",
        "nm": 165157224,
        "avg_position": 0
      },
      {
        "date": "2024-10-08T03:00:00+03:00",
        "nm": 165157224,
        "avg_position": 0
      },
      {
        "date": "2024-10-08T03:00:00+03:00",
        "nm": 165157224,
        "avg_position": 0
      },
      {
        "date": "2024-10-08T03:00:00+03:00",
        "nm": 165157224,
        "avg_position": 0
      },
      {
        "date": "2024-10-08T03:00:00+03:00",
        "nm": 165157224,
        "avg_position": 0
      },
      {
        "date": "2024-10-08T03:00:00+03:00",
        "nm": 165157224,
        "avg_position": 0
      },
      {
        "date": "2024-10-08T03:00:00+03:00",
        "nm": 165157224,
        "avg_position": 0
      },
      {
        "date": "2024-10-08T03:00:00+03:00",
        "nm": 165157224,
        "avg_position": 0
      },
      {
        "date": "2024-10-08T03:00:00+03:00",
        "nm": 165157224,
        "avg_position": 0
      },
      {
        "date": "2024-10-08T03:00:00+03:00",
        "nm": 165157224,
        "avg_position": 0
      },
      {
        "date": "2024-10-08T03:00:00+03:00",
        "nm": 165157224,
        "avg_position": 0
      },
      {
        "date": "2024-10-08T03:00:00+03:00",
        "nm": 165157224,
        "avg_position": 0
      },
      {
        "date": "2024-10-08T03:00:00+03:00",
        "nm": 165157224,
        "avg_position": 0
      },
      {
        "date": "2024-10-08T03:00:00+03:00",
        "nm": 165157224,
        "avg_position": 0
      },
      {
        "date": "2024-10-08T03:00:00+03:00",
        "nm": 165157224,
        "avg_position": 0
      },
      {
        "date": "2024-10-08T03:00:00+03:00",
        "nm": 165157224,
        "avg_position": 0
      },
      {
        "date": "2024-10-08T03:00:00+03:00",
        "nm": 165157224,
        "avg_position": 0
      },
      {
        "date": "2024-10-08T03:00:00+03:00",
        "nm": 165157224,
        "avg_position": 0
      },
      {
        "date": "2024-10-08T03:00:00+03:00",
        "nm": 165157224,
        "avg_position": 0
      },
      {
        "date": "2024-10-08T03:00:00+03:00",
        "nm": 165157224,
        "avg_position": 0
      },
      {
        "date": "2024-10-08T03:00:00+03:00",
        "nm": 235991430,
        "avg_position": 0
      },
      {
        "date": "2024-10-08T03:00:00+03:00",
        "nm": 186652711,
        "avg_position": 0
      },
      {
        "date": "2024-10-08T03:00:00+03:00",
        "nm": 158418726,
        "avg_position": 0
      },
      {
        "date": "2024-10-08T03:00:00+03:00",
        "nm": 237721514,
        "avg_position": 0
      },
      {
        "date": "2024-10-08T03:00:00+03:00",
        "nm": 233046636,
        "avg_position": 0
      },
      {
        "date": "2024-10-08T03:00:00+03:00",
        "nm": 147497597,
        "avg_position": 0
      },
      {
        "date": "2024-10-08T03:00:00+03:00",
        "nm": 200021733,
        "avg_position": 0
      },
      {
        "date": "2024-10-08T03:00:00+03:00",
        "nm": 208178050,
        "avg_position": 0
      },
      {
        "date": "2024-10-08T03:00:00+03:00",
        "nm": 233234033,
        "avg_position": 0
      },
      {
        "date": "2024-10-08T03:00:00+03:00",
        "nm": 165158543,
        "avg_position": 0
      },
      {
        "date": "2024-10-08T03:00:00+03:00",
        "nm": 142913532,
        "avg_position": 0
      },
      {
        "date": "2024-10-08T03:00:00+03:00",
        "nm": 186652711,
        "avg_position": 0
      },
      {
        "date": "2024-10-08T03:00:00+03:00",
        "nm": 209127437,
        "avg_position": 0
      },
      {
        "date": "2024-10-08T03:00:00+03:00",
        "nm": 237721514,
        "avg_position": 0
      },
      {
        "date": "2024-10-08T03:00:00+03:00",
        "nm": 233234033,
        "avg_position": 0
      },
      {
        "date": "2024-10-08T03:00:00+03:00",
        "nm": 147497597,
        "avg_position": 0
      },
      {
        "date": "2024-10-08T03:00:00+03:00",
        "nm": 200021733,
        "avg_position": 0
      },
      {
        "date": "2024-10-08T03:00:00+03:00",
        "nm": 237721514,
        "avg_position": 0
      },
      {
        "date": "2024-10-08T03:00:00+03:00",
        "nm": 218974848,
        "avg_position": 0
      },
      {
        "date": "2024-10-08T03:00:00+03:00",
        "nm": 147497597,
        "avg_position": 0
      },
      {
        "date": "2024-10-08T03:00:00+03:00",
        "nm": 186652711,
        "avg_position": 0
      },
      {
        "date": "2024-10-08T03:00:00+03:00",
        "nm": 233046636,
        "avg_position": 0
      },
      {
        "date": "2024-10-08T03:00:00+03:00",
        "nm": 147497597,
        "avg_position": 0
      },
      {
        "date": "2024-10-08T03:00:00+03:00",
        "nm": 237721514,
        "avg_position": 0
      },
      {
        "date": "2024-10-08T03:00:00+03:00",
        "nm": 208178050,
        "avg_position": 0
      },
      {
        "date": "2024-10-08T03:00:00+03:00",
        "nm": 208178050,
        "avg_position": 0
      },
      {
        "date": "2024-10-08T03:00:00+03:00",
        "nm": 186652711,
        "avg_position": 0
      },
      {
        "date": "2024-10-08T03:00:00+03:00",
        "nm": 233046636,
        "avg_position": 0
      },
      {
        "date": "2024-10-08T03:00:00+03:00",
        "nm": 200021733,
        "avg_position": 0
      },
      {
        "date": "2024-10-08T03:00:00+03:00",
        "nm": 142913532,
        "avg_position": 0
      }
    ],
    "advertId": 19447497
  }
]
